itester/__init__.py
itester/itester.py
itester/test_main.py
itester/common/__init__.py
itester/common/html_report.py
itester/common/parameterized.py
itester/common/termlogcolor.py
itester/common/tools.py
itester-1.0.5.dist-info/DESCRIPTION.rst
itester-1.0.5.dist-info/METADATA
itester-1.0.5.dist-info/RECORD
itester-1.0.5.dist-info/WHEEL
itester-1.0.5.dist-info/entry_points.txt
itester-1.0.5.dist-info/metadata.json
itester-1.0.5.dist-info/top_level.txt
