Metadata-Version: 2.0
Name: itester
Version: 1.0.5
Summary: Excel - driven interface automation framework
Home-page: https://github.com/mxgnene01/itester
Author: Xiangguo Meng
Author-email: mxgnene01@gmail.com
License: GNU
Platform: UNKNOWN
Requires-Dist: click
Requires-Dist: requests
Requires-Dist: xlrd
